{
  "title": "GraphQL avec REST & gestion de cache",
  "slug": "apollo-rest-cache",
  "permalink": "/fr/apollo-rest-cache",
  "excerpt": "Dans ce tutoriel nous allons voir comment mettre en place un serveur graphql en récupérant les données via des APIs REST, et comment optimiser notre application",
  "stepTitles": [
    "Introduction",
    "Apollo serveur",
    "Apollo client",
    "Options de cache"
  ],
  "date": "2019-05-10",
  "authors": [
    {
      "name": "Marie Minasyan",
      "username": "marishka"
    }
  ],
  "category": [
    "Apollo",
    "GraphQL",
    "React",
    "Node"
  ],
  "tags": [
    "GraphQL",
    "Apollo"
  ]
}
